[
  {
    "equipmentId": 1
  },
  {
    "equipmentId": 2,
    "status": "Disponible"
  },
  {
    "equipmentId": 3,
    "status": "Mantenimiento"
  },
  {
    "equipmentId": 4,
    "status": "En Uso"
  },
  {
    "equipmentId": 7,
    "name": "Camera EOS R5",
    "description": "Cámara Profesional Canon",
    "status": "Disponible"
  },
  {
    "equipmentId": 8,
    "name": "Camera EOS R5",
    "description": "Cámara Profesional Canon",
    "status": "Disponible"
  },
  {
    "equipmentId": 9,
    "name": "Camera EOS R5",
    "description": "Cámara Profesional Canon",
    "status": "Disponible"
  },
  {
    "equipmentId": 10,
    "name": "Camera EOS R5",
    "description": "Cámara Profesional Canon",
    "status": "Disponible"
  },
  {
    "equipmentId": 11,
    "name": "Camera EOS R5",
    "description": "Cámara Profesional Canon",
    "status": "Disponible"
  },
  {
    "equipmentId": 12,
    "name": "Camera EOS R5",
    "description": "Cámara Profesional Canon",
    "status": "Disponible"
  },
  {
    "equipmentId": 13,
    "name": "Camera EOS R5",
    "description": "Cámara Profesional Canon",
    "status": "Disponible"
  },
  {
    "equipmentId": 14,
    "name": "Camera EOS R5",
    "description": "Cámara Profesional Canon",
    "status": "Disponible"
  },
  {
    "equipmentId": 15,
    "name": "Camera EOS R5",
    "description": "Cámara Profesional Canon",
    "status": "Disponible"
  },
  {
    "equipmentId": 16,
    "name": "Camera EOS R5",
    "description": "Cámara Profesional Canon",
    "status": "Disponible"
  },
  {
    "equipmentId": 17,
    "name": "Camera EOS R5",
    "description": "Cámara Profesional Canon",
    "status": "Disponible"
  },
  {
    "equipmentId": 18,
    "name": "Camera EOS R5",
    "description": "Cámara Profesional Canon",
    "status": "Disponible"
  },
  {
    "equipmentId": 19,
    "name": "Camera EOS R5",
    "description": "Cámara Profesional Canon",
    "status": "Disponible"
  },
  {
    "equipmentId": 20,
    "name": "Camera EOS R5",
    "description": "Cámara Profesional Canon",
    "status": "Disponible"
  },
  {
    "equipmentId": 21,
    "name": "Camera EOS R5",
    "description": "Cámara Profesional Canon",
    "status": "Disponible"
  },
  {
    "equipmentId": 22,
    "name": "Camera EOS R5",
    "description": "Cámara Profesional Canon",
    "status": "Disponible"
  },
  {
    "equipmentId": 23,
    "name": "Camera EOS R5",
    "description": "Cámara Profesional Canon",
    "status": "Disponible"
  },
  {
    "equipmentId": 24,
    "name": "Softbox 90cm",
    "description": "Iluminación Suave",
    "status": "Disponible"
  },
  {
    "equipmentId": 25,
    "name": "Softbox 90cm",
    "description": "Iluminación Suave",
    "status": "Disponible"
  },
  {
    "equipmentId": 26,
    "name": "Softbox 90cm",
    "description": "Iluminación Suave",
    "status": "Disponible"
  },
  {
    "equipmentId": 27,
    "name": "Softbox 90cm",
    "description": "Iluminación Suave",
    "status": "Disponible"
  },
  {
    "equipmentId": 28,
    "name": "Softbox 90cm",
    "description": "Iluminación Suave",
    "status": "Disponible"
  },
  {
    "equipmentId": 29,
    "name": "Camera EOS R5",
    "description": "Cámara Profesional Canon",
    "status": "Disponible"
  },
  {
    "equipmentId": 30,
    "name": "Tripod PRO X",
    "description": "Trípode de Aluminio",
    "status": "Disponible"
  },
  {
    "equipmentId": 31,
    "name": "Microphone Shotgun",
    "description": "Micrófono Direccional",
    "status": "Disponible"
  },
  {
    "equipmentId": 32,
    "name": "Tripod PRO X",
    "description": "Trípode de Aluminio",
    "status": "Disponible"
  },
  {
    "equipmentId": 33,
    "name": "LED Light Panel",
    "description": "Iluminación Suave",
    "status": "Disponible"
  },
  {
    "equipmentId": 34,
    "name": "Microphone Shotgun",
    "description": "Micrófono Direccional",
    "status": "Disponible"
  },
  {
    "equipmentId": 35,
    "name": "Softbox 90cm",
    "description": "Iluminación Suave",
    "status": "Disponible"
  },
  {
    "equipmentId": 36,
    "name": "Camera EOS R5",
    "description": "Cámara Profesional Canon",
    "status": "Disponible"
  },
  {
    "equipmentId": 37,
    "name": "Camera EOS R5",
    "description": "Cámara Profesional Canon",
    "status": "En Uso"
  },
  {
    "equipmentId": 38,
    "name": "LED Light Panel",
    "description": "Iluminación Suave",
    "status": "En Uso"
  },
  {
    "equipmentId": 39,
    "name": "Tripod PRO X",
    "description": "Trípode de Aluminio",
    "status": "En Uso"
  },
  {
    "equipmentId": 40,
    "name": "LED Light Panel",
    "description": "Iluminación Suave",
    "status": "Disponible"
  },
  {
    "equipmentId": 41,
    "name": "Camera EOS R5",
    "description": "Cámara Profesional Canon",
    "status": "Disponible"
  },
  {
    "equipmentId": 42,
    "name": "Camera EOS R5",
    "description": "Cámara Profesional Canon",
    "status": "Disponible"
  },
  {
    "equipmentId": 43,
    "name": "Tripod PRO X",
    "description": "Trípode de Aluminio",
    "status": "Disponible"
  },
  {
    "equipmentId": 44,
    "name": "LED Light Panel",
    "description": "Iluminación Suave",
    "status": "Disponible"
  },
  {
    "equipmentId": 45,
    "name": "Microphone Shotgun",
    "description": "Micrófono Direccional",
    "status": "Disponible"
  }
]